MANIFEST.in
README.rst
setup.py
waves_gateway/__init__.py
waves_gateway/gateway.py
waves_gateway.egg-info/PKG-INFO
waves_gateway.egg-info/SOURCES.txt
waves_gateway.egg-info/dependency_links.txt
waves_gateway.egg-info/requires.txt
waves_gateway.egg-info/top_level.txt
waves_gateway/common/__init__.py
waves_gateway/common/exceptions.py
waves_gateway/common/injector.py
waves_gateway/common/proxy_factory.py
waves_gateway/common/proxy_guard.py
waves_gateway/common/token.py
waves_gateway/common/utils.py
waves_gateway/controller/__init__.py
waves_gateway/controller/flask_rest_controller.py
waves_gateway/controller/gateway_controller.py
waves_gateway/controller/gateway_controller_converter_proxy_impl.py
waves_gateway/controller/gateway_controller_impl.py
waves_gateway/factory/__init__.py
waves_gateway/factory/coin_address_factory.py
waves_gateway/model/__init__.py
waves_gateway/model/attempt_list_query.py
waves_gateway/model/gateway_config_file.py
waves_gateway/model/key_pair.py
waves_gateway/model/mapping_entry.py
waves_gateway/model/polling_delay_config.py
waves_gateway/model/polling_state.py
waves_gateway/model/public_configuration.py
waves_gateway/model/transaction.py
waves_gateway/model/transaction_attempt.py
waves_gateway/model/transaction_attempt_list.py
waves_gateway/serializer/__init__.py
waves_gateway/serializer/key_pair_serializer.py
waves_gateway/serializer/mapping_entry_serializer.py
waves_gateway/serializer/polling_state_serializer.py
waves_gateway/serializer/polling_transaction_state_serializer.py
waves_gateway/serializer/public_configuration_serializer.py
waves_gateway/serializer/serializer.py
waves_gateway/serializer/transaction_attempt_list_serializer.py
waves_gateway/service/__init__.py
waves_gateway/service/address_validation_service.py
waves_gateway/service/asset_transaction_service_impl.py
waves_gateway/service/attempt_list_converter_service.py
waves_gateway/service/attempt_list_worker.py
waves_gateway/service/chain_query_service.py
waves_gateway/service/chain_query_service_converter_proxy_impl.py
waves_gateway/service/coin_transaction_consumer_impl.py
waves_gateway/service/constant_fee_service_impl.py
