Metadata-Version: 1.2
Name: waves-gateway
Version: 1.0.4
Summary: A framework to connect other cryptocurrencies to the Waves-Platform.
Home-page: https://github.com/jansenmarc/WavesGatewayFramework
Author: Henning Gerrits
License: MIT
Keywords: waves gateway wavesplatform
Platform: UNKNOWN
Requires-Python: >=3.5
